{"title":"Horny Lesbian Fuck Hottie Latin","uid":15257755,"size":54290271,"categoryP":"porn","categoryS":"movie_clips","magnet":"?xt=urn:btih:0d93d6af883af12df7b90a512ec43d3eef6799cc&amp;dn=Horny+Lesbian+Fuck+Hottie+Latin&amp;tr=udp%3A%2F%2Ftracker.leechers-paradise.org%3A6969&amp;tr=udp%3A%2F%2Fzer0day.ch%3A1337&amp;tr=udp%3A%2F%2Fopen.demonii.com%3A1337&amp;tr=udp%3A%2F%2Ftracker.coppersurfer.tk%3A6969&amp;tr=udp%3A%2F%2Fexodus.desync.com%3A6969","seeders":0,"leechers":1,"uploader":"demonoidt","files":1,"time":1468145750,"description":"Samples\r\n \nhttp://adultwallpapers.co.in/horny-lesbian-fuck-hottie-latin/\r\n \nhttp://demonoid.co/2016/07/10/horny-lesbian-fuck-hottie-latin/","torrent":{"xt":"urn:btih:0d93d6af883af12df7b90a512ec43d3eef6799cc","amp;dn":"Horny+Lesbian+Fuck+Hottie+Latin","amp;tr":["udp%3A%2F%2Ftracker.leechers-paradise.org%3A6969","udp%3A%2F%2Fzer0day.ch%3A1337","udp%3A%2F%2Fopen.demonii.com%3A1337","udp%3A%2F%2Ftracker.coppersurfer.tk%3A6969","udp%3A%2F%2Fexodus.desync.com%3A6969"],"infoHash":"0d93d6af883af12df7b90a512ec43d3eef6799cc","infoHashBuffer":{"type":"Buffer","data":[13,147,214,175,136,58,241,45,247,185,10,81,46,196,61,62,239,103,153,204]},"announce":[],"urlList":[]}}