{"title":"PunishTeens - Maya Bijou.mp4","uid":15710712,"size":617057630,"categoryP":"porn","categoryS":"movie_clips","magnet":"?xt=urn:btih:19a49fc326a33410b578241fa394e24f217fd64d&amp;dn=PunishTeens+-+Maya+Bijou.mp4&amp;tr=udp%3A%2F%2Ftracker.leechers-paradise.org%3A6969&amp;tr=udp%3A%2F%2Fzer0day.ch%3A1337&amp;tr=udp%3A%2F%2Fopen.demonii.com%3A1337&amp;tr=udp%3A%2F%2Ftracker.coppersurfer.tk%3A6969&amp;tr=udp%3A%2F%2Fexodus.desync.com%3A6969","seeders":0,"leechers":4,"uploader":"Pr0nmaster","files":1,"time":1472565070,"description":"PunishTeens - Maya Bijou.mp4\r\n\r\n588.47 MB \r\n\r\nScreens\r\n \nhttp://imgcentral.com/viewer.php?file=54197945490664479708.jpg\r\n \nhttp://imgcentral.com/viewer.php?file=43690558010259327614.jpg\r\n \nhttp://imgcentral.com/viewer.php?file=18208767205387479712.jpg\r\n \nhttp://imgcentral.com/viewer.php?file=17528596823101481210.jpg","torrent":{"xt":"urn:btih:19a49fc326a33410b578241fa394e24f217fd64d","amp;dn":"PunishTeens+-+Maya+Bijou.mp4","amp;tr":["udp%3A%2F%2Ftracker.leechers-paradise.org%3A6969","udp%3A%2F%2Fzer0day.ch%3A1337","udp%3A%2F%2Fopen.demonii.com%3A1337","udp%3A%2F%2Ftracker.coppersurfer.tk%3A6969","udp%3A%2F%2Fexodus.desync.com%3A6969"],"infoHash":"19a49fc326a33410b578241fa394e24f217fd64d","infoHashBuffer":{"type":"Buffer","data":[25,164,159,195,38,163,52,16,181,120,36,31,163,148,226,79,33,127,214,77]},"announce":[],"urlList":[]}}