{"title":"African Girl and BBC Fuckin n Suckin","uid":15656622,"size":86752600,"categoryP":"porn","categoryS":"movie_clips","magnet":"?xt=urn:btih:1cb7f879aa8c1ef157cdead0c6811bdbebd513a9&amp;dn=African+Girl+and+BBC+Fuckin+n+Suckin&amp;tr=udp%3A%2F%2Ftracker.leechers-paradise.org%3A6969&amp;tr=udp%3A%2F%2Fzer0day.ch%3A1337&amp;tr=udp%3A%2F%2Fopen.demonii.com%3A1337&amp;tr=udp%3A%2F%2Ftracker.coppersurfer.tk%3A6969&amp;tr=udp%3A%2F%2Fexodus.desync.com%3A6969","seeders":0,"leechers":1,"uploader":"demonoidt","files":1,"time":1472142905,"description":"Samples\r\n \nhttp://adultwallpapers.co.in/african-girl-and-bbc-fuckin-n-suckin/\r\n \nhttp://demonoid.co/2016/08/25/african-girl-and-bbc-fuckin-n-suckin/","torrent":{"xt":"urn:btih:1cb7f879aa8c1ef157cdead0c6811bdbebd513a9","amp;dn":"African+Girl+and+BBC+Fuckin+n+Suckin","amp;tr":["udp%3A%2F%2Ftracker.leechers-paradise.org%3A6969","udp%3A%2F%2Fzer0day.ch%3A1337","udp%3A%2F%2Fopen.demonii.com%3A1337","udp%3A%2F%2Ftracker.coppersurfer.tk%3A6969","udp%3A%2F%2Fexodus.desync.com%3A6969"],"infoHash":"1cb7f879aa8c1ef157cdead0c6811bdbebd513a9","infoHashBuffer":{"type":"Buffer","data":[28,183,248,121,170,140,30,241,87,205,234,208,198,129,27,219,235,213,19,169]},"announce":[],"urlList":[]}}