{"title":"Stephen.Colbert.2016.08.25.Tim.Kaine.480p.x264-mSD","uid":15668584,"size":272904256,"categoryP":"video","categoryS":"tv_shows","magnet":"?xt=urn:btih:1f140be6ff950dd91894a30553af4ad2b8fe5190&amp;dn=Stephen.Colbert.2016.08.25.Tim.Kaine.480p.x264-mSD&amp;tr=udp%3A%2F%2Ftracker.leechers-paradise.org%3A6969&amp;tr=udp%3A%2F%2Fzer0day.ch%3A1337&amp;tr=udp%3A%2F%2Fopen.demonii.com%3A1337&amp;tr=udp%3A%2F%2Ftracker.coppersurfer.tk%3A6969&amp;tr=udp%3A%2F%2Fexodus.desync.com%3A6969","seeders":0,"leechers":1,"uploader":"TvTeam","files":7,"time":1472222962,"description":"------------------------------------------------------------------------\r\n\r  https://www.torrenting.com\r\n\r\nSign up is OPEN - for time being. Come and have fun.\r\nHurry up sign up is open now!!!!","torrent":{"xt":"urn:btih:1f140be6ff950dd91894a30553af4ad2b8fe5190","amp;dn":"Stephen.Colbert.2016.08.25.Tim.Kaine.480p.x264-mSD","amp;tr":["udp%3A%2F%2Ftracker.leechers-paradise.org%3A6969","udp%3A%2F%2Fzer0day.ch%3A1337","udp%3A%2F%2Fopen.demonii.com%3A1337","udp%3A%2F%2Ftracker.coppersurfer.tk%3A6969","udp%3A%2F%2Fexodus.desync.com%3A6969"],"infoHash":"1f140be6ff950dd91894a30553af4ad2b8fe5190","infoHashBuffer":{"type":"Buffer","data":[31,20,11,230,255,149,13,217,24,148,163,5,83,175,74,210,184,254,81,144]},"announce":[],"urlList":[]}}