{"title":"latina Luna Star loves to fuck","uid":15656303,"size":149837792,"categoryP":"porn","categoryS":"movie_clips","magnet":"?xt=urn:btih:202ff03aad89912197b3cb04a7eb9f087d719cde&amp;dn=latina+Luna+Star+loves+to+fuck&amp;tr=udp%3A%2F%2Ftracker.leechers-paradise.org%3A6969&amp;tr=udp%3A%2F%2Fzer0day.ch%3A1337&amp;tr=udp%3A%2F%2Fopen.demonii.com%3A1337&amp;tr=udp%3A%2F%2Ftracker.coppersurfer.tk%3A6969&amp;tr=udp%3A%2F%2Fexodus.desync.com%3A6969","seeders":0,"leechers":2,"uploader":"luciano_x","files":1,"time":1472138310,"description":"SCREENSHOTS \nhttp://imghall.com/?v=8qjbb5mhf4n2.jpg\r\n \nhttp://imghall.com/?v=57b89273ee751.jpg\r\n\r\n\r\n\r\nGet More Small Sized XXX Videos \nhttps://thepiratebay.org/user/luciano_x","torrent":{"xt":"urn:btih:202ff03aad89912197b3cb04a7eb9f087d719cde","amp;dn":"latina+Luna+Star+loves+to+fuck","amp;tr":["udp%3A%2F%2Ftracker.leechers-paradise.org%3A6969","udp%3A%2F%2Fzer0day.ch%3A1337","udp%3A%2F%2Fopen.demonii.com%3A1337","udp%3A%2F%2Ftracker.coppersurfer.tk%3A6969","udp%3A%2F%2Fexodus.desync.com%3A6969"],"infoHash":"202ff03aad89912197b3cb04a7eb9f087d719cde","infoHashBuffer":{"type":"Buffer","data":[32,47,240,58,173,137,145,33,151,179,203,4,167,235,159,8,125,113,156,222]},"announce":[],"urlList":[]}}