{"title":"Original.Sin-Sex.S01E02.Government.in.the.Bedroom.XviD-AFG","uid":15340053,"size":733096714,"categoryP":"video","categoryS":"tv_shows","magnet":"?xt=urn:btih:3cbb9aeeb1f35a85e16c339356bbd9cc3e4ed32b&amp;dn=Original.Sin-Sex.S01E02.Government.in.the.Bedroom.XviD-AFG&amp;tr=udp%3A%2F%2Ftracker.leechers-paradise.org%3A6969&amp;tr=udp%3A%2F%2Fzer0day.ch%3A1337&amp;tr=udp%3A%2F%2Fopen.demonii.com%3A1337&amp;tr=udp%3A%2F%2Ftracker.coppersurfer.tk%3A6969&amp;tr=udp%3A%2F%2Fexodus.desync.com%3A6969","seeders":0,"leechers":1,"uploader":"TvTeam","files":7,"time":1468827757,"description":"https://www.torrenting.com\r\n\r\nSign up is OPEN - for time being. Come and have fun","torrent":{"xt":"urn:btih:3cbb9aeeb1f35a85e16c339356bbd9cc3e4ed32b","amp;dn":"Original.Sin-Sex.S01E02.Government.in.the.Bedroom.XviD-AFG","amp;tr":["udp%3A%2F%2Ftracker.leechers-paradise.org%3A6969","udp%3A%2F%2Fzer0day.ch%3A1337","udp%3A%2F%2Fopen.demonii.com%3A1337","udp%3A%2F%2Ftracker.coppersurfer.tk%3A6969","udp%3A%2F%2Fexodus.desync.com%3A6969"],"infoHash":"3cbb9aeeb1f35a85e16c339356bbd9cc3e4ed32b","infoHashBuffer":{"type":"Buffer","data":[60,187,154,238,177,243,90,133,225,108,51,147,86,187,217,204,62,78,211,43]},"announce":[],"urlList":[]}}