{"title":"German groupsex bukkake orgy","uid":15225172,"size":185798423,"categoryP":"porn","categoryS":"movie_clips","magnet":"?xt=urn:btih:43c900b68bddcb231f9b09a1543140ecbdbea320&amp;dn=German+groupsex+bukkake+orgy&amp;tr=udp%3A%2F%2Ftracker.leechers-paradise.org%3A6969&amp;tr=udp%3A%2F%2Fzer0day.ch%3A1337&amp;tr=udp%3A%2F%2Fopen.demonii.com%3A1337&amp;tr=udp%3A%2F%2Ftracker.coppersurfer.tk%3A6969&amp;tr=udp%3A%2F%2Fexodus.desync.com%3A6969","seeders":0,"leechers":1,"uploader":"luciano_x","files":1,"time":1467760431,"description":"SCREENSHOTS \nhttp://panustudio.site/image/CrF\r\n \nhttp://panustudio.site/image/CrV\r\n \nhttp://panustudio.site/image/Crb\r\n\r\n\r\n\r\nGet More Small Sized XXX Videos \nhttps://thepiratebay.org/user/luciano_x","torrent":{"xt":"urn:btih:43c900b68bddcb231f9b09a1543140ecbdbea320","amp;dn":"German+groupsex+bukkake+orgy","amp;tr":["udp%3A%2F%2Ftracker.leechers-paradise.org%3A6969","udp%3A%2F%2Fzer0day.ch%3A1337","udp%3A%2F%2Fopen.demonii.com%3A1337","udp%3A%2F%2Ftracker.coppersurfer.tk%3A6969","udp%3A%2F%2Fexodus.desync.com%3A6969"],"infoHash":"43c900b68bddcb231f9b09a1543140ecbdbea320","infoHashBuffer":{"type":"Buffer","data":[67,201,0,182,139,221,203,35,31,155,9,161,84,49,64,236,189,190,163,32]},"announce":[],"urlList":[]}}