{"title":"35 Japanese big tits look through door sex","uid":15787876,"size":175256802,"categoryP":"porn","categoryS":"movie_clips","magnet":"?xt=urn:btih:558859f23b8b0882ea1c12f7e08b6586a669e318&amp;dn=35+Japanese+big+tits+look+through+door+sex&amp;tr=udp%3A%2F%2Ftracker.leechers-paradise.org%3A6969&amp;tr=udp%3A%2F%2Fzer0day.ch%3A1337&amp;tr=udp%3A%2F%2Fopen.demonii.com%3A1337&amp;tr=udp%3A%2F%2Ftracker.coppersurfer.tk%3A6969&amp;tr=udp%3A%2F%2Fexodus.desync.com%3A6969","seeders":0,"leechers":1,"uploader":"demonoidt","files":1,"time":1473347018,"description":"Samples\r\n \nhttp://adultwallpapers.co.in/35-japanese-big-tits-look-through-door-sex/\r\n \nhttp://demonoid.co/2016/09/08/35-japanese-big-tits-look-through-door-sex/","torrent":{"xt":"urn:btih:558859f23b8b0882ea1c12f7e08b6586a669e318","amp;dn":"35+Japanese+big+tits+look+through+door+sex","amp;tr":["udp%3A%2F%2Ftracker.leechers-paradise.org%3A6969","udp%3A%2F%2Fzer0day.ch%3A1337","udp%3A%2F%2Fopen.demonii.com%3A1337","udp%3A%2F%2Ftracker.coppersurfer.tk%3A6969","udp%3A%2F%2Fexodus.desync.com%3A6969"],"infoHash":"558859f23b8b0882ea1c12f7e08b6586a669e318","infoHashBuffer":{"type":"Buffer","data":[85,136,89,242,59,139,8,130,234,28,18,247,224,139,101,134,166,105,227,24]},"announce":[],"urlList":[]}}