{"title":"Nicole Bexley Sucks Cock","uid":15802829,"size":106711108,"categoryP":"porn","categoryS":"movie_clips","magnet":"?xt=urn:btih:561dbd12bd134a92288dd6127e0dab6bd18ac2fa&amp;dn=Nicole+Bexley+Sucks+Cock&amp;tr=udp%3A%2F%2Ftracker.leechers-paradise.org%3A6969&amp;tr=udp%3A%2F%2Fzer0day.ch%3A1337&amp;tr=udp%3A%2F%2Fopen.demonii.com%3A1337&amp;tr=udp%3A%2F%2Ftracker.coppersurfer.tk%3A6969&amp;tr=udp%3A%2F%2Fexodus.desync.com%3A6969","seeders":0,"leechers":1,"uploader":"demonoidt","files":1,"time":1473529457,"description":"Samples\r\n \nhttp://adultwallpapers.co.in/nicole-bexley-sucks-cock/\r\n \nhttp://demonoid.co/2016/09/10/nicole-bexley-sucks-cock/","torrent":{"xt":"urn:btih:561dbd12bd134a92288dd6127e0dab6bd18ac2fa","amp;dn":"Nicole+Bexley+Sucks+Cock","amp;tr":["udp%3A%2F%2Ftracker.leechers-paradise.org%3A6969","udp%3A%2F%2Fzer0day.ch%3A1337","udp%3A%2F%2Fopen.demonii.com%3A1337","udp%3A%2F%2Ftracker.coppersurfer.tk%3A6969","udp%3A%2F%2Fexodus.desync.com%3A6969"],"infoHash":"561dbd12bd134a92288dd6127e0dab6bd18ac2fa","infoHashBuffer":{"type":"Buffer","data":[86,29,189,18,189,19,74,146,40,141,214,18,126,13,171,107,209,138,194,250]},"announce":[],"urlList":[]}}