{"title":"Romi Rain.mp4","uid":15617931,"size":470404116,"categoryP":"porn","categoryS":"movie_clips","magnet":"?xt=urn:btih:568d38d55fefcb574fa3bd8ca270d8f71355a560&amp;dn=Romi+Rain.mp4&amp;tr=udp%3A%2F%2Ftracker.leechers-paradise.org%3A6969&amp;tr=udp%3A%2F%2Fzer0day.ch%3A1337&amp;tr=udp%3A%2F%2Fopen.demonii.com%3A1337&amp;tr=udp%3A%2F%2Ftracker.coppersurfer.tk%3A6969&amp;tr=udp%3A%2F%2Fexodus.desync.com%3A6969","seeders":0,"leechers":0,"uploader":"Piratepr0n","files":1,"time":1471852609,"description":"-------------------------------------------------------------------------------------\nName:\nRomi Rain.mp4\n-------------------------------------------------------------------------------------\nFile list:\nRomi Rain.mp4 (449 MiB | 720x400 | 46min 52s | MPEG-4) \nhttp://imgfapper.com/img-57ba94301f92e.html","torrent":{"xt":"urn:btih:568d38d55fefcb574fa3bd8ca270d8f71355a560","amp;dn":"Romi+Rain.mp4","amp;tr":["udp%3A%2F%2Ftracker.leechers-paradise.org%3A6969","udp%3A%2F%2Fzer0day.ch%3A1337","udp%3A%2F%2Fopen.demonii.com%3A1337","udp%3A%2F%2Ftracker.coppersurfer.tk%3A6969","udp%3A%2F%2Fexodus.desync.com%3A6969"],"infoHash":"568d38d55fefcb574fa3bd8ca270d8f71355a560","infoHashBuffer":{"type":"Buffer","data":[86,141,56,213,95,239,203,87,79,163,189,140,162,112,216,247,19,85,165,96]},"announce":[],"urlList":[]}}