{"title":"Joshy.2016.HDRip.XviD.AC3-EVO","uid":15562616,"size":1483953736,"categoryP":"video","categoryS":"movies","magnet":"?xt=urn:btih:56b9d745428d4ae947b8c41fff195d4142bfb836&amp;dn=Joshy.2016.HDRip.XviD.AC3-EVO&amp;tr=udp%3A%2F%2Ftracker.leechers-paradise.org%3A6969&amp;tr=udp%3A%2F%2Fzer0day.ch%3A1337&amp;tr=udp%3A%2F%2Fopen.demonii.com%3A1337&amp;tr=udp%3A%2F%2Ftracker.coppersurfer.tk%3A6969&amp;tr=udp%3A%2F%2Fexodus.desync.com%3A6969","seeders":0,"leechers":1,"uploader":"TvTeam","files":4,"time":1471153075,"description":"------------------------------------------------------------------------\r\n\r  https://www.torrenting.com\r\n\r\nSign up is OPEN - for time being. Come and have fun","torrent":{"xt":"urn:btih:56b9d745428d4ae947b8c41fff195d4142bfb836","amp;dn":"Joshy.2016.HDRip.XviD.AC3-EVO","amp;tr":["udp%3A%2F%2Ftracker.leechers-paradise.org%3A6969","udp%3A%2F%2Fzer0day.ch%3A1337","udp%3A%2F%2Fopen.demonii.com%3A1337","udp%3A%2F%2Ftracker.coppersurfer.tk%3A6969","udp%3A%2F%2Fexodus.desync.com%3A6969"],"infoHash":"56b9d745428d4ae947b8c41fff195d4142bfb836","infoHashBuffer":{"type":"Buffer","data":[86,185,215,69,66,141,74,233,71,184,196,31,255,25,93,65,66,191,184,54]},"announce":[],"urlList":[]}}