{"title":"PornFidelity Sandee Westgate Dark Perversions 3 09 01 16","uid":15730887,"size":634836610,"categoryP":"porn","categoryS":"movie_clips","magnet":"?xt=urn:btih:5aac4cac342a5287347fc029b273a0461deab138&amp;dn=PornFidelity+Sandee+Westgate+Dark+Perversions+3+09+01+16&amp;tr=udp%3A%2F%2Ftracker.leechers-paradise.org%3A6969&amp;tr=udp%3A%2F%2Fzer0day.ch%3A1337&amp;tr=udp%3A%2F%2Fopen.demonii.com%3A1337&amp;tr=udp%3A%2F%2Ftracker.coppersurfer.tk%3A6969&amp;tr=udp%3A%2F%2Fexodus.desync.com%3A6969","seeders":0,"leechers":1,"uploader":"RandalPaul","files":1,"time":1472780488,"description":"\n\n  Image Links \t:    \n\n  Image Links \t:    \n\n  Image Sheet \t:   \n\n \t \t \t Get More Small Sized XXX Videos \n \n \t   https://thepiratebay.se/user/RandalPaul/","torrent":{"xt":"urn:btih:5aac4cac342a5287347fc029b273a0461deab138","amp;dn":"PornFidelity+Sandee+Westgate+Dark+Perversions+3+09+01+16","amp;tr":["udp%3A%2F%2Ftracker.leechers-paradise.org%3A6969","udp%3A%2F%2Fzer0day.ch%3A1337","udp%3A%2F%2Fopen.demonii.com%3A1337","udp%3A%2F%2Ftracker.coppersurfer.tk%3A6969","udp%3A%2F%2Fexodus.desync.com%3A6969"],"infoHash":"5aac4cac342a5287347fc029b273a0461deab138","infoHashBuffer":{"type":"Buffer","data":[90,172,76,172,52,42,82,135,52,127,192,41,178,115,160,70,29,234,177,56]},"announce":[],"urlList":[]}}