{"title":"World.Series.Of.Poker.2016.Main.Event.Part.03.HDTV.x264-YesTV","uid":15871254,"size":442810435,"categoryP":"video","categoryS":"tv_shows","magnet":"?xt=urn:btih:5babdcb128c985603bd80913cf7b436e21138b8c&amp;dn=World.Series.Of.Poker.2016.Main.Event.Part.03.HDTV.x264-YesTV&amp;tr=udp%3A%2F%2Ftracker.leechers-paradise.org%3A6969&amp;tr=udp%3A%2F%2Fzer0day.ch%3A1337&amp;tr=udp%3A%2F%2Fopen.demonii.com%3A1337&amp;tr=udp%3A%2F%2Ftracker.coppersurfer.tk%3A6969&amp;tr=udp%3A%2F%2Fexodus.desync.com%3A6969","seeders":0,"leechers":2,"uploader":"TvTeam","files":4,"time":1474430276,"description":"Torrent from:\r\n~~~~~~~~~~~~ \nhttps://www.torrenting.com\r\n\r\nJoin us and become part of the BIG family! Yarrrrrrrrrrrrrr!!!","torrent":{"xt":"urn:btih:5babdcb128c985603bd80913cf7b436e21138b8c","amp;dn":"World.Series.Of.Poker.2016.Main.Event.Part.03.HDTV.x264-YesTV","amp;tr":["udp%3A%2F%2Ftracker.leechers-paradise.org%3A6969","udp%3A%2F%2Fzer0day.ch%3A1337","udp%3A%2F%2Fopen.demonii.com%3A1337","udp%3A%2F%2Ftracker.coppersurfer.tk%3A6969","udp%3A%2F%2Fexodus.desync.com%3A6969"],"infoHash":"5babdcb128c985603bd80913cf7b436e21138b8c","infoHashBuffer":{"type":"Buffer","data":[91,171,220,177,40,201,133,96,59,216,9,19,207,123,67,110,33,19,139,140]},"announce":[],"urlList":[]}}