{"title":"Two Cute Butts And Horny Bull In Threesome Sex mp4","uid":15767569,"size":374608164,"categoryP":"porn","categoryS":"movie_clips","magnet":"?xt=urn:btih:6ee5cff8eafc91cb6cf5eb1fdf9415f457d0de9f&amp;dn=Two+Cute+Butts+And+Horny+Bull+In+Threesome+Sex+mp4&amp;tr=udp%3A%2F%2Ftracker.leechers-paradise.org%3A6969&amp;tr=udp%3A%2F%2Fzer0day.ch%3A1337&amp;tr=udp%3A%2F%2Fopen.demonii.com%3A1337&amp;tr=udp%3A%2F%2Ftracker.coppersurfer.tk%3A6969&amp;tr=udp%3A%2F%2Fexodus.desync.com%3A6969","seeders":0,"leechers":2,"uploader":"RandalPaul","files":1,"time":1473170914,"description":"\n\n  Image Links \t:  http://imgshag.com/image/G5mN3  \n\n  Image Links \t:  http://imgshag.com/image/G5hXA  \n\n  Image Sheet \t:  http://imgshag.com/image/G5wQn \n\n \t \t \t Get More Small Sized XXX Videos \n \n \t   https://thepiratebay.se/user/RandalPaul/","torrent":{"xt":"urn:btih:6ee5cff8eafc91cb6cf5eb1fdf9415f457d0de9f","amp;dn":"Two+Cute+Butts+And+Horny+Bull+In+Threesome+Sex+mp4","amp;tr":["udp%3A%2F%2Ftracker.leechers-paradise.org%3A6969","udp%3A%2F%2Fzer0day.ch%3A1337","udp%3A%2F%2Fopen.demonii.com%3A1337","udp%3A%2F%2Ftracker.coppersurfer.tk%3A6969","udp%3A%2F%2Fexodus.desync.com%3A6969"],"infoHash":"6ee5cff8eafc91cb6cf5eb1fdf9415f457d0de9f","infoHashBuffer":{"type":"Buffer","data":[110,229,207,248,234,252,145,203,108,245,235,31,223,148,21,244,87,208,222,159]},"announce":[],"urlList":[]}}