{"title":"Errotica-Archives Lizzie Fade Into You XXX 1080p 16.07.17","uid":15338061,"size":310566536,"categoryP":"porn","categoryS":"hd___movies","magnet":"?xt=urn:btih:76c5eed5a247d968854041bc3681c9e05d9f4d9c&amp;dn=Errotica-Archives+Lizzie+Fade+Into+You+XXX+1080p+16.07.17&amp;tr=udp%3A%2F%2Ftracker.leechers-paradise.org%3A6969&amp;tr=udp%3A%2F%2Fzer0day.ch%3A1337&amp;tr=udp%3A%2F%2Fopen.demonii.com%3A1337&amp;tr=udp%3A%2F%2Ftracker.coppersurfer.tk%3A6969&amp;tr=udp%3A%2F%2Fexodus.desync.com%3A6969","seeders":0,"leechers":1,"uploader":"thfatboys","files":1,"time":1468797763,"description":"Screens: \nhttp://imgpeak.com/img-578bedb0a6af7.html","torrent":{"xt":"urn:btih:76c5eed5a247d968854041bc3681c9e05d9f4d9c","amp;dn":"Errotica-Archives+Lizzie+Fade+Into+You+XXX+1080p+16.07.17","amp;tr":["udp%3A%2F%2Ftracker.leechers-paradise.org%3A6969","udp%3A%2F%2Fzer0day.ch%3A1337","udp%3A%2F%2Fopen.demonii.com%3A1337","udp%3A%2F%2Ftracker.coppersurfer.tk%3A6969","udp%3A%2F%2Fexodus.desync.com%3A6969"],"infoHash":"76c5eed5a247d968854041bc3681c9e05d9f4d9c","infoHashBuffer":{"type":"Buffer","data":[118,197,238,213,162,71,217,104,133,64,65,188,54,129,201,224,93,159,77,156]},"announce":[],"urlList":[]}}