{"title":"Angel Rivas mais uma vez encarando o pauzão de","uid":15654216,"size":106880760,"categoryP":"porn","categoryS":"movie_clips","magnet":"?xt=urn:btih:7bd2ae00583492be86a085e57fba447eeb465379&amp;dn=Angel+Rivas+mais+uma+vez+encarando+o+pauz%26atilde%3Bo+de&amp;tr=udp%3A%2F%2Ftracker.leechers-paradise.org%3A6969&amp;tr=udp%3A%2F%2Fzer0day.ch%3A1337&amp;tr=udp%3A%2F%2Fopen.demonii.com%3A1337&amp;tr=udp%3A%2F%2Ftracker.coppersurfer.tk%3A6969&amp;tr=udp%3A%2F%2Fexodus.desync.com%3A6969","seeders":0,"leechers":4,"uploader":"demonoidt","files":1,"time":1472126276,"description":"Samples\r\n \nhttp://adultwallpapers.co.in/angel-rivas-mais-uma-vez-encarando-o-pauzao-de-nick-moreno/\r\n \nhttp://demonoid.co/2016/08/25/angel-rivas-mais-uma-vez-encarando-o-pauzao-de-nick-moreno/","torrent":{"xt":"urn:btih:7bd2ae00583492be86a085e57fba447eeb465379","amp;dn":"Angel+Rivas+mais+uma+vez+encarando+o+pauz%26atilde%3Bo+de","amp;tr":["udp%3A%2F%2Ftracker.leechers-paradise.org%3A6969","udp%3A%2F%2Fzer0day.ch%3A1337","udp%3A%2F%2Fopen.demonii.com%3A1337","udp%3A%2F%2Ftracker.coppersurfer.tk%3A6969","udp%3A%2F%2Fexodus.desync.com%3A6969"],"infoHash":"7bd2ae00583492be86a085e57fba447eeb465379","infoHashBuffer":{"type":"Buffer","data":[123,210,174,0,88,52,146,190,134,160,133,229,127,186,68,126,235,70,83,121]},"announce":[],"urlList":[]}}