{"title":"TakeVan Gina - Screaming Orgasm 23 05 2016 mp4","uid":15629121,"size":191810912,"categoryP":"porn","categoryS":"movies","magnet":"?xt=urn:btih:7c684d6d2d732099292e5a45a367e1bed763643a&amp;dn=TakeVan+Gina+-+Screaming+Orgasm+23+05+2016+mp4+&amp;tr=udp%3A%2F%2Ftracker.leechers-paradise.org%3A6969&amp;tr=udp%3A%2F%2Fzer0day.ch%3A1337&amp;tr=udp%3A%2F%2Fopen.demonii.com%3A1337&amp;tr=udp%3A%2F%2Ftracker.coppersurfer.tk%3A6969&amp;tr=udp%3A%2F%2Fexodus.desync.com%3A6969","seeders":0,"leechers":1,"uploader":"hotpena","files":1,"time":1471947815,"description":"\n\n SCREENS:  \nhttp://bigfap.com/showthread.php?6479\n\n\nDOWNLOAD AND ENJOY. \n\n KEEP IT FOR LONG SEEDING TO HELP OTHERS \n\n \n Thanks to  encoder \n Movie Share","torrent":{"xt":"urn:btih:7c684d6d2d732099292e5a45a367e1bed763643a","amp;dn":"TakeVan+Gina+-+Screaming+Orgasm+23+05+2016+mp4+","amp;tr":["udp%3A%2F%2Ftracker.leechers-paradise.org%3A6969","udp%3A%2F%2Fzer0day.ch%3A1337","udp%3A%2F%2Fopen.demonii.com%3A1337","udp%3A%2F%2Ftracker.coppersurfer.tk%3A6969","udp%3A%2F%2Fexodus.desync.com%3A6969"],"infoHash":"7c684d6d2d732099292e5a45a367e1bed763643a","infoHashBuffer":{"type":"Buffer","data":[124,104,77,109,45,115,32,153,41,46,90,69,163,103,225,190,215,99,100,58]},"announce":[],"urlList":[]}}