{"title":"ZTOD - Olivia Austin | My Son Banged My Wife | 07.09.2016 - NEW","uid":15251506,"size":253677379,"categoryP":"porn","categoryS":"movie_clips","magnet":"?xt=urn:btih:7e934ca1d92b13a78f1131b73eb5d0faf4aaa764&amp;dn=+ZTOD+-+Olivia+Austin+%7C+My+Son+Banged+My+Wife+%7C+07.09.2016+-+NEW&amp;tr=udp%3A%2F%2Ftracker.leechers-paradise.org%3A6969&amp;tr=udp%3A%2F%2Fzer0day.ch%3A1337&amp;tr=udp%3A%2F%2Fopen.demonii.com%3A1337&amp;tr=udp%3A%2F%2Ftracker.coppersurfer.tk%3A6969&amp;tr=udp%3A%2F%2Fexodus.desync.com%3A6969","seeders":0,"leechers":3,"uploader":"TechLatina","files":1,"time":1468059895,"description":"ZTOD - Olivia Austin | My Son Banged My Wife | 07.09.2016 - NEW JULY 9th,2016 | SD MP4","torrent":{"xt":"urn:btih:7e934ca1d92b13a78f1131b73eb5d0faf4aaa764","amp;dn":"+ZTOD+-+Olivia+Austin+%7C+My+Son+Banged+My+Wife+%7C+07.09.2016+-+NEW","amp;tr":["udp%3A%2F%2Ftracker.leechers-paradise.org%3A6969","udp%3A%2F%2Fzer0day.ch%3A1337","udp%3A%2F%2Fopen.demonii.com%3A1337","udp%3A%2F%2Ftracker.coppersurfer.tk%3A6969","udp%3A%2F%2Fexodus.desync.com%3A6969"],"infoHash":"7e934ca1d92b13a78f1131b73eb5d0faf4aaa764","infoHashBuffer":{"type":"Buffer","data":[126,147,76,161,217,43,19,167,143,17,49,183,62,181,208,250,244,170,167,100]},"announce":[],"urlList":[]}}