{"title":"Red Faction - Armageddon Complete Edition {DZREPACK}","uid":15656296,"size":6333661184,"categoryP":"games","categoryS":"pc","magnet":"?xt=urn:btih:94844aa835e0c4008ceeddbb1016255b0cf4b84a&amp;dn=Red+Faction+-+Armageddon+Complete+Edition+%7BDZREPACK%7D&amp;tr=udp%3A%2F%2Ftracker.leechers-paradise.org%3A6969&amp;tr=udp%3A%2F%2Fzer0day.ch%3A1337&amp;tr=udp%3A%2F%2Fopen.demonii.com%3A1337&amp;tr=udp%3A%2F%2Ftracker.coppersurfer.tk%3A6969&amp;tr=udp%3A%2F%2Fexodus.desync.com%3A6969","seeders":0,"leechers":2,"uploader":"taylorswiftfreak","files":1,"time":1472138209,"description":"ABOUT THE GAME\r\n\r\nHalf a century after the Red Faction resistance and their Marauder allies freed Mars from the brutal Earth Defense Force, harmony on Mars is again threatened but this time by a lethal force shrouded in mystery.\r\n\r\nTitle: Red Faction Armageddon\r\nGenre: Action\r\nDeveloper: Volition\r\nPublisher: Nordic Games\r\nRelease Date: 9 Jun, 2011\r\nLanguages: EN\r\n\r\nFinal size............:8.56 GB\r\n\r\nRepacked size ..........:5.89GB  Including Soundtrack\r\n\r\nvideos..................:Lossless\r\n\r\naudio...................:Lossless\r\n\r\ntexture.................:Lossless\r\n\r\nNote: The game is updated to v1.01.\r\n\r\nThis complete release includes:\r\n• Red Faction: Armageddon (main game)\r\n• Path to War DLC\r\n• Soundtrack\r\n\r\nBased on the PROPHET Release\r\n\r\ncredits:\r\nmik3y\r\nrepacked By mik3y\r\nHuge Thanks to Our Programmers : Razor12911 and Panker1992","torrent":{"xt":"urn:btih:94844aa835e0c4008ceeddbb1016255b0cf4b84a","amp;dn":"Red+Faction+-+Armageddon+Complete+Edition+%7BDZREPACK%7D","amp;tr":["udp%3A%2F%2Ftracker.leechers-paradise.org%3A6969","udp%3A%2F%2Fzer0day.ch%3A1337","udp%3A%2F%2Fopen.demonii.com%3A1337","udp%3A%2F%2Ftracker.coppersurfer.tk%3A6969","udp%3A%2F%2Fexodus.desync.com%3A6969"],"infoHash":"94844aa835e0c4008ceeddbb1016255b0cf4b84a","infoHashBuffer":{"type":"Buffer","data":[148,132,74,168,53,224,196,0,140,238,221,187,16,22,37,91,12,244,184,74]},"announce":[],"urlList":[]}}