{"title":"Deep double penetration for naughty Lea Lexus","uid":15445152,"size":255694886,"categoryP":"porn","categoryS":"movie_clips","magnet":"?xt=urn:btih:9b4a81393a83e3cad5f629b0626de509ad92ce78&amp;dn=Deep+double+penetration+for+naughty+Lea+Lexus&amp;tr=udp%3A%2F%2Ftracker.leechers-paradise.org%3A6969&amp;tr=udp%3A%2F%2Fzer0day.ch%3A1337&amp;tr=udp%3A%2F%2Fopen.demonii.com%3A1337&amp;tr=udp%3A%2F%2Ftracker.coppersurfer.tk%3A6969&amp;tr=udp%3A%2F%2Fexodus.desync.com%3A6969","seeders":0,"leechers":2,"uploader":"luciano_x","files":1,"time":1469870593,"description":"SCREENSHOTS \nhttp://panustudio.site/viewer.php?file=96646627363346336004.jpg\r\n \nhttp://panustudio.site/viewer.php?file=63326076057375923254.jpg\r\n \nhttp://panustudio.site/viewer.php?file=87217284966537892059.jpg\r\n\r\n\r\n\r\nGet More Small Sized XXX Videos \nhttps://thepiratebay.org/user/luciano_x","torrent":{"xt":"urn:btih:9b4a81393a83e3cad5f629b0626de509ad92ce78","amp;dn":"Deep+double+penetration+for+naughty+Lea+Lexus","amp;tr":["udp%3A%2F%2Ftracker.leechers-paradise.org%3A6969","udp%3A%2F%2Fzer0day.ch%3A1337","udp%3A%2F%2Fopen.demonii.com%3A1337","udp%3A%2F%2Ftracker.coppersurfer.tk%3A6969","udp%3A%2F%2Fexodus.desync.com%3A6969"],"infoHash":"9b4a81393a83e3cad5f629b0626de509ad92ce78","infoHashBuffer":{"type":"Buffer","data":[155,74,129,57,58,131,227,202,213,246,41,176,98,109,229,9,173,146,206,120]},"announce":[],"urlList":[]}}