{"title":"1841MeaMeloneFuckMachine","uid":15743616,"size":205135221,"categoryP":"porn","categoryS":"movie_clips","magnet":"?xt=urn:btih:a2cd8c21e7291ef884881054a78f679e64fa843a&amp;dn=1841MeaMeloneFuckMachine&amp;tr=udp%3A%2F%2Ftracker.leechers-paradise.org%3A6969&amp;tr=udp%3A%2F%2Fzer0day.ch%3A1337&amp;tr=udp%3A%2F%2Fopen.demonii.com%3A1337&amp;tr=udp%3A%2F%2Ftracker.coppersurfer.tk%3A6969&amp;tr=udp%3A%2F%2Fexodus.desync.com%3A6969","seeders":0,"leechers":1,"uploader":"RandalPaul","files":1,"time":1472943144,"description":"\n\n  Image Links \t:  http://imgshag.com/image/GFbpa  \n\n  Image Links \t:  http://imgshag.com/image/GF3UD  \n\n  Image Sheet \t:  http://imgshag.com/image/GFFSp \n\n \t \t \t Get More Small Sized XXX Videos \n \n \t   https://thepiratebay.se/user/RandalPaul/","torrent":{"xt":"urn:btih:a2cd8c21e7291ef884881054a78f679e64fa843a","amp;dn":"1841MeaMeloneFuckMachine","amp;tr":["udp%3A%2F%2Ftracker.leechers-paradise.org%3A6969","udp%3A%2F%2Fzer0day.ch%3A1337","udp%3A%2F%2Fopen.demonii.com%3A1337","udp%3A%2F%2Ftracker.coppersurfer.tk%3A6969","udp%3A%2F%2Fexodus.desync.com%3A6969"],"infoHash":"a2cd8c21e7291ef884881054a78f679e64fa843a","infoHashBuffer":{"type":"Buffer","data":[162,205,140,33,231,41,30,248,132,136,16,84,167,143,103,158,100,250,132,58]},"announce":[],"urlList":[]}}