{"title":"WickedPictures Suicide Squad An Axel Braun Parody 720p MP4-KTR","uid":15480478,"size":2418569903,"categoryP":"porn","categoryS":"hd___movies","magnet":"?xt=urn:btih:a9d07d0aae77e05220284e34016b799c6f174d53&amp;dn=WickedPictures+Suicide+Squad+An+Axel+Braun+Parody+720p+MP4-KTR&amp;tr=udp%3A%2F%2Ftracker.leechers-paradise.org%3A6969&amp;tr=udp%3A%2F%2Fzer0day.ch%3A1337&amp;tr=udp%3A%2F%2Fopen.demonii.com%3A1337&amp;tr=udp%3A%2F%2Ftracker.coppersurfer.tk%3A6969&amp;tr=udp%3A%2F%2Fexodus.desync.com%3A6969","seeders":0,"leechers":1,"uploader":"hotpena","files":50,"time":1470246075,"description":"\n\n SCREENS:  \nhttp://bigfap.com/showthread.php?4139\n\n\nDOWNLOAD AND ENJOY. \n\n KEEP IT FOR LONG SEEDING TO HELP OTHERS \n\n \n Thanks to  encoder \n Movie Share","torrent":{"xt":"urn:btih:a9d07d0aae77e05220284e34016b799c6f174d53","amp;dn":"WickedPictures+Suicide+Squad+An+Axel+Braun+Parody+720p+MP4-KTR","amp;tr":["udp%3A%2F%2Ftracker.leechers-paradise.org%3A6969","udp%3A%2F%2Fzer0day.ch%3A1337","udp%3A%2F%2Fopen.demonii.com%3A1337","udp%3A%2F%2Ftracker.coppersurfer.tk%3A6969","udp%3A%2F%2Fexodus.desync.com%3A6969"],"infoHash":"a9d07d0aae77e05220284e34016b799c6f174d53","infoHashBuffer":{"type":"Buffer","data":[169,208,125,10,174,119,224,82,32,40,78,52,1,107,121,156,111,23,77,83]},"announce":[],"urlList":[]}}