{"title":"Reality Kings - 2016-07-15 - 8th Street Latinas - Maya Bijou mp4","uid":15333228,"size":424094319,"categoryP":"porn","categoryS":"movies","magnet":"?xt=urn:btih:ad8f0c3a6f22b35846a979d849ae5b9008a043f2&amp;dn=Reality+Kings+-+2016-07-15+-+8th+Street+Latinas+-+Maya+Bijou+mp4&amp;tr=udp%3A%2F%2Ftracker.leechers-paradise.org%3A6969&amp;tr=udp%3A%2F%2Fzer0day.ch%3A1337&amp;tr=udp%3A%2F%2Fopen.demonii.com%3A1337&amp;tr=udp%3A%2F%2Ftracker.coppersurfer.tk%3A6969&amp;tr=udp%3A%2F%2Fexodus.desync.com%3A6969","seeders":0,"leechers":0,"uploader":"hotpena","files":1,"time":1468759407,"description":"\n\n SCREENS:  \nhttp://bigfap.com/showthread.php?1962\n\n\nDOWNLOAD AND ENJOY. \n\n KEEP IT FOR LONG SEEDING TO HELP OTHERS \n\n \n Thanks to  encoder \n Movie Share","torrent":{"xt":"urn:btih:ad8f0c3a6f22b35846a979d849ae5b9008a043f2","amp;dn":"Reality+Kings+-+2016-07-15+-+8th+Street+Latinas+-+Maya+Bijou+mp4","amp;tr":["udp%3A%2F%2Ftracker.leechers-paradise.org%3A6969","udp%3A%2F%2Fzer0day.ch%3A1337","udp%3A%2F%2Fopen.demonii.com%3A1337","udp%3A%2F%2Ftracker.coppersurfer.tk%3A6969","udp%3A%2F%2Fexodus.desync.com%3A6969"],"infoHash":"ad8f0c3a6f22b35846a979d849ae5b9008a043f2","infoHashBuffer":{"type":"Buffer","data":[173,143,12,58,111,34,179,88,70,169,121,216,73,174,91,144,8,160,67,242]},"announce":[],"urlList":[]}}