{"title":"BlacksOnBlondes: Bibi Noel XXX [264]","uid":15461981,"size":429159168,"categoryP":"porn","categoryS":"movie_clips","magnet":"?xt=urn:btih:c057107098c30e7a8581566f91d03556b75d2375&amp;dn=BlacksOnBlondes%3A+Bibi+Noel+XXX+%5B264%5D&amp;tr=udp%3A%2F%2Ftracker.leechers-paradise.org%3A6969&amp;tr=udp%3A%2F%2Fzer0day.ch%3A1337&amp;tr=udp%3A%2F%2Fopen.demonii.com%3A1337&amp;tr=udp%3A%2F%2Ftracker.coppersurfer.tk%3A6969&amp;tr=udp%3A%2F%2Fexodus.desync.com%3A6969","seeders":0,"leechers":0,"uploader":"Piratepr0n","files":1,"time":1470057388,"description":"-------------------------------------------------------------------------------------\nName:\nBlacksOnBlondes: Bibi Noel XXX [264]\n-------------------------------------------------------------------------------------\nFile list:\nbibi_noel_2_720p_med.mp4 (409 MiB | 768x432 | 34min 50s | MPEG-4) \nhttp://imgfapper.com/img-579f2fae7a267.html","torrent":{"xt":"urn:btih:c057107098c30e7a8581566f91d03556b75d2375","amp;dn":"BlacksOnBlondes%3A+Bibi+Noel+XXX+%5B264%5D","amp;tr":["udp%3A%2F%2Ftracker.leechers-paradise.org%3A6969","udp%3A%2F%2Fzer0day.ch%3A1337","udp%3A%2F%2Fopen.demonii.com%3A1337","udp%3A%2F%2Ftracker.coppersurfer.tk%3A6969","udp%3A%2F%2Fexodus.desync.com%3A6969"],"infoHash":"c057107098c30e7a8581566f91d03556b75d2375","infoHashBuffer":{"type":"Buffer","data":[192,87,16,112,152,195,14,122,133,129,86,111,145,208,53,86,183,93,35,117]},"announce":[],"urlList":[]}}