{"title":"DrunkSexOrgy DSO Alter Ego Orgy Part 7 Cam 1","uid":15782648,"size":501870645,"categoryP":"porn","categoryS":"movie_clips","magnet":"?xt=urn:btih:c6e99ebc7b5e342d2174868bfded866c049b9cc8&amp;dn=DrunkSexOrgy+DSO+Alter+Ego+Orgy+Part+7+Cam+1&amp;tr=udp%3A%2F%2Ftracker.leechers-paradise.org%3A6969&amp;tr=udp%3A%2F%2Fzer0day.ch%3A1337&amp;tr=udp%3A%2F%2Fopen.demonii.com%3A1337&amp;tr=udp%3A%2F%2Ftracker.coppersurfer.tk%3A6969&amp;tr=udp%3A%2F%2Fexodus.desync.com%3A6969","seeders":0,"leechers":1,"uploader":"RandalPaul","files":1,"time":1473297754,"description":"\n\n  Image Links \t:  http://imgshag.com/image/GzVci  \n\n  Image Links \t:  http://imgshag.com/image/GzRqd  \n\n  Image Sheet \t:  http://imgshag.com/image/GzzgY \n\n \t \t \t Get More Small Sized XXX Videos \n \n \t   https://thepiratebay.se/user/RandalPaul/","torrent":{"xt":"urn:btih:c6e99ebc7b5e342d2174868bfded866c049b9cc8","amp;dn":"DrunkSexOrgy+DSO+Alter+Ego+Orgy+Part+7+Cam+1","amp;tr":["udp%3A%2F%2Ftracker.leechers-paradise.org%3A6969","udp%3A%2F%2Fzer0day.ch%3A1337","udp%3A%2F%2Fopen.demonii.com%3A1337","udp%3A%2F%2Ftracker.coppersurfer.tk%3A6969","udp%3A%2F%2Fexodus.desync.com%3A6969"],"infoHash":"c6e99ebc7b5e342d2174868bfded866c049b9cc8","infoHashBuffer":{"type":"Buffer","data":[198,233,158,188,123,94,52,45,33,116,134,139,253,237,134,108,4,155,156,200]},"announce":[],"urlList":[]}}