{"title":"[ClubSandy] - Kenzie Taylor, John Strong - You Caught Me! [NEW A","uid":15616742,"size":542346245,"categoryP":"porn","categoryS":"movie_clips","magnet":"?xt=urn:btih:c85f311153f22974a5044db01e2f315c7e025ec8&amp;dn=%5BClubSandy%5D+-+Kenzie+Taylor%2C+John+Strong+-+You+Caught+Me%21+%5BNEW+A&amp;tr=udp%3A%2F%2Ftracker.leechers-paradise.org%3A6969&amp;tr=udp%3A%2F%2Fzer0day.ch%3A1337&amp;tr=udp%3A%2F%2Fopen.demonii.com%3A1337&amp;tr=udp%3A%2F%2Ftracker.coppersurfer.tk%3A6969&amp;tr=udp%3A%2F%2Fexodus.desync.com%3A6969","seeders":0,"leechers":1,"uploader":"LucasCar","files":1,"time":1471834436,"description":"[ClubSandy] - Kenzie Taylor, John Strong - You Caught Me! [NEW August 21, 2016]\r\n\r\nJohn Strong never knew his girlfriend Kenzie Taylor was into anal, and neither did she, until he caught her with her finger up her ass for the first time! Since she’s already horny and the thought of catching her gets John horny too, they decide to shove his big cock in her ass and see how it can spice up their love life!\r\n \nhttp://screenimage.net/img-57ba4d3eb28bb.html\r\n \nhttp://screenimage.net/img-57ba4d41e59e7.html\r\n\r\n\r\n\r\n★ ★ ★  For more Exclusive Porn please visit ★ ★ ★\r\n    \nhttps://thepiratebay.org/user/LucasCar","torrent":{"xt":"urn:btih:c85f311153f22974a5044db01e2f315c7e025ec8","amp;dn":"%5BClubSandy%5D+-+Kenzie+Taylor%2C+John+Strong+-+You+Caught+Me%21+%5BNEW+A","amp;tr":["udp%3A%2F%2Ftracker.leechers-paradise.org%3A6969","udp%3A%2F%2Fzer0day.ch%3A1337","udp%3A%2F%2Fopen.demonii.com%3A1337","udp%3A%2F%2Ftracker.coppersurfer.tk%3A6969","udp%3A%2F%2Fexodus.desync.com%3A6969"],"infoHash":"c85f311153f22974a5044db01e2f315c7e025ec8","infoHashBuffer":{"type":"Buffer","data":[200,95,49,17,83,242,41,116,165,4,77,176,30,47,49,92,126,2,94,200]},"announce":[],"urlList":[]}}