{"title":"IndustryInvaders.14.11.11.Mena.Li.XXX.1080p.MP4-KTR[N1C]","uid":15652771,"size":1080599611,"categoryP":"porn","categoryS":"other","magnet":"?xt=urn:btih:d2f403ea36431605f94908eae6f63396e7e69136&amp;dn=IndustryInvaders.14.11.11.Mena.Li.XXX.1080p.MP4-KTR%5BN1C%5D&amp;tr=udp%3A%2F%2Ftracker.leechers-paradise.org%3A6969&amp;tr=udp%3A%2F%2Fzer0day.ch%3A1337&amp;tr=udp%3A%2F%2Fopen.demonii.com%3A1337&amp;tr=udp%3A%2F%2Ftracker.coppersurfer.tk%3A6969&amp;tr=udp%3A%2F%2Fexodus.desync.com%3A6969","seeders":0,"leechers":1,"uploader":"juggs99","files":3,"time":1472113717,"description":"\nIndustryInvaders.14.11.11.Mena.Li.XXX.1080p.MP4-KTR \r\n\n\n[Format]:    MPEG-4\n[Duration]:    27mn 30s\n[Resolution]:  1 920 x 1 080 pixels\n[Display aspect ratio]:    16:9\n[Frame rate mode]:    Constant\n[Frame rate]:    30.000 fps\n\r\n\n#N1C -&gt; To avoid fakes, ALWAYS check that the torrent was added by NO1CARES\r \nhttp://extratorrent.cc/\r\n\n\nHelp us by donating with Bitcoin: 1XeH1kKXWYbzZcFHokGiZ4d3MWW5WyXzU\r\n\nScreens...\r \nhttp://www.xxximagetpb.org/image/wet07\r \nhttp://www.xxximagetpb.org/image/we2mb\r \nhttp://www.xxximagetpb.org/image/weHBh\r \nhttp://www.xxximagetpb.org/image/weTbn","torrent":{"xt":"urn:btih:d2f403ea36431605f94908eae6f63396e7e69136","amp;dn":"IndustryInvaders.14.11.11.Mena.Li.XXX.1080p.MP4-KTR%5BN1C%5D","amp;tr":["udp%3A%2F%2Ftracker.leechers-paradise.org%3A6969","udp%3A%2F%2Fzer0day.ch%3A1337","udp%3A%2F%2Fopen.demonii.com%3A1337","udp%3A%2F%2Ftracker.coppersurfer.tk%3A6969","udp%3A%2F%2Fexodus.desync.com%3A6969"],"infoHash":"d2f403ea36431605f94908eae6f63396e7e69136","infoHashBuffer":{"type":"Buffer","data":[210,244,3,234,54,67,22,5,249,73,8,234,230,246,51,150,231,230,145,54]},"announce":[],"urlList":[]}}