{"title":"Bosch.S02E02.480p.x264-mSD","uid":15578055,"size":203784958,"categoryP":"video","categoryS":"tv_shows","magnet":"?xt=urn:btih:dcb660d8b44b89bb1d45e6e8aa05a958ab5337ca&amp;dn=Bosch.S02E02.480p.x264-mSD&amp;tr=udp%3A%2F%2Ftracker.leechers-paradise.org%3A6969&amp;tr=udp%3A%2F%2Fzer0day.ch%3A1337&amp;tr=udp%3A%2F%2Fopen.demonii.com%3A1337&amp;tr=udp%3A%2F%2Ftracker.coppersurfer.tk%3A6969&amp;tr=udp%3A%2F%2Fexodus.desync.com%3A6969","seeders":0,"leechers":1,"uploader":"TvTeam","files":7,"time":1471367042,"description":"------------------------------------------------------------------------\r\n\r  https://www.torrenting.com\r\n\r\nSign up is OPEN - for time being. Come and have fun.\r\nHurry up sign up is open now!!!!","torrent":{"xt":"urn:btih:dcb660d8b44b89bb1d45e6e8aa05a958ab5337ca","amp;dn":"Bosch.S02E02.480p.x264-mSD","amp;tr":["udp%3A%2F%2Ftracker.leechers-paradise.org%3A6969","udp%3A%2F%2Fzer0day.ch%3A1337","udp%3A%2F%2Fopen.demonii.com%3A1337","udp%3A%2F%2Ftracker.coppersurfer.tk%3A6969","udp%3A%2F%2Fexodus.desync.com%3A6969"],"infoHash":"dcb660d8b44b89bb1d45e6e8aa05a958ab5337ca","infoHashBuffer":{"type":"Buffer","data":[220,182,96,216,180,75,137,187,29,69,230,232,170,5,169,88,171,83,55,202]},"announce":[],"urlList":[]}}