{"title":"IHaveaWife Brooklyn Chase 720p mp4 12 July 2016","uid":15283461,"size":1121862537,"categoryP":"porn","categoryS":"hd___movies","magnet":"?xt=urn:btih:ecd9782413d7dc0cba5e54e13483d03107211019&amp;dn=IHaveaWife+Brooklyn+Chase+720p+mp4+12+July+2016+&amp;tr=udp%3A%2F%2Ftracker.leechers-paradise.org%3A6969&amp;tr=udp%3A%2F%2Fzer0day.ch%3A1337&amp;tr=udp%3A%2F%2Fopen.demonii.com%3A1337&amp;tr=udp%3A%2F%2Ftracker.coppersurfer.tk%3A6969&amp;tr=udp%3A%2F%2Fexodus.desync.com%3A6969","seeders":0,"leechers":1,"uploader":"thfatboys","files":1,"time":1468361045,"description":"Screens: \nhttp://imgpeak.com/img-57853c86b442e.html","torrent":{"xt":"urn:btih:ecd9782413d7dc0cba5e54e13483d03107211019","amp;dn":"IHaveaWife+Brooklyn+Chase+720p+mp4+12+July+2016+","amp;tr":["udp%3A%2F%2Ftracker.leechers-paradise.org%3A6969","udp%3A%2F%2Fzer0day.ch%3A1337","udp%3A%2F%2Fopen.demonii.com%3A1337","udp%3A%2F%2Ftracker.coppersurfer.tk%3A6969","udp%3A%2F%2Fexodus.desync.com%3A6969"],"infoHash":"ecd9782413d7dc0cba5e54e13483d03107211019","infoHashBuffer":{"type":"Buffer","data":[236,217,120,36,19,215,220,12,186,94,84,225,52,131,208,49,7,33,16,25]},"announce":[],"urlList":[]}}