{"title":"Titlicious 2.avi","uid":15307551,"size":245246399,"categoryP":"porn","categoryS":"movie_clips","magnet":"?xt=urn:btih:effb756e523e34f07794eb1bc4cb734354a46308&amp;dn=Titlicious+2.avi&amp;tr=udp%3A%2F%2Ftracker.leechers-paradise.org%3A6969&amp;tr=udp%3A%2F%2Fzer0day.ch%3A1337&amp;tr=udp%3A%2F%2Fopen.demonii.com%3A1337&amp;tr=udp%3A%2F%2Ftracker.coppersurfer.tk%3A6969&amp;tr=udp%3A%2F%2Fexodus.desync.com%3A6969","seeders":0,"leechers":0,"uploader":"Piratepr0n","files":1,"time":1468540235,"description":"-------------------------------------------------------------------------------------\nName:\nTitlicious 2.avi\n-------------------------------------------------------------------------------------\nFile list:\nTitlicious 2.avi (234 MiB | 624x352 | 26min 30s | AVI) \nhttp://imgfapper.com/img-5788094e7b303.html","torrent":{"xt":"urn:btih:effb756e523e34f07794eb1bc4cb734354a46308","amp;dn":"Titlicious+2.avi","amp;tr":["udp%3A%2F%2Ftracker.leechers-paradise.org%3A6969","udp%3A%2F%2Fzer0day.ch%3A1337","udp%3A%2F%2Fopen.demonii.com%3A1337","udp%3A%2F%2Ftracker.coppersurfer.tk%3A6969","udp%3A%2F%2Fexodus.desync.com%3A6969"],"infoHash":"effb756e523e34f07794eb1bc4cb734354a46308","infoHashBuffer":{"type":"Buffer","data":[239,251,117,110,82,62,52,240,119,148,235,27,196,203,115,67,84,164,99,8]},"announce":[],"urlList":[]}}