{"title":"County.Calendar.2016.09.10.HDTV.x264-FiHTV","uid":15801719,"size":208318994,"categoryP":"video","categoryS":"tv_shows","magnet":"?xt=urn:btih:f7d4501b3fec4c575a7c551d2594d63bb23f62a9&amp;dn=County.Calendar.2016.09.10.HDTV.x264-FiHTV&amp;tr=udp%3A%2F%2Ftracker.leechers-paradise.org%3A6969&amp;tr=udp%3A%2F%2Fzer0day.ch%3A1337&amp;tr=udp%3A%2F%2Fopen.demonii.com%3A1337&amp;tr=udp%3A%2F%2Ftracker.coppersurfer.tk%3A6969&amp;tr=udp%3A%2F%2Fexodus.desync.com%3A6969","seeders":0,"leechers":0,"uploader":"TvTeam","files":4,"time":1473514773,"description":"Torrent from:\r\n~~~~~~~~~~~~ \nhttps://www.torrenting.com\r\n\r\nJoin us and become part of the BIG family! Yarrrrrrrrrrrrrr!!!","torrent":{"xt":"urn:btih:f7d4501b3fec4c575a7c551d2594d63bb23f62a9","amp;dn":"County.Calendar.2016.09.10.HDTV.x264-FiHTV","amp;tr":["udp%3A%2F%2Ftracker.leechers-paradise.org%3A6969","udp%3A%2F%2Fzer0day.ch%3A1337","udp%3A%2F%2Fopen.demonii.com%3A1337","udp%3A%2F%2Ftracker.coppersurfer.tk%3A6969","udp%3A%2F%2Fexodus.desync.com%3A6969"],"infoHash":"f7d4501b3fec4c575a7c551d2594d63bb23f62a9","infoHashBuffer":{"type":"Buffer","data":[247,212,80,27,63,236,76,87,90,124,85,29,37,148,214,59,178,63,98,169]},"announce":[],"urlList":[]}}